{"name":"MJ asdasd",
"profile_name":"mjasdasd",
"profile_url":"https://teamtreehouse.com/profiles/mjasdasd",
"gravatar_url":"https://secure.gravatar.com/avatar/64b441d960cc887df3203c97c8f01c01?s=400\u0026d=https%3A%2F%2Fstatic.teamtreehouse.com%2Fassets%2Fcontent%2Fdefault_avatar-ea7cf6abde4eec089a4e03cc925d0e893e428b2b6971b12405a9b118c837eaa2.png\u0026r=pg",
"gravatar_hash":"64b441d960cc887df3203c97c8f01c01",
"badges":[{"id":49,
"name":"Newbie",
"url":"https://teamtreehouse.com/profiles/mjasdasd",
"icon_url":"https://achievement-images.teamtreehouse.com/Generic_Newbie.png",
"earned_date":"2023-02-22T12:10:38.000Z","courses":[]},
{"id":16012,
"name":"Meet Python",
"url":"https://teamtreehouse.com/library/python-basics-3/meet-python",
"icon_url":"https://achievement-images.teamtreehouse.com/badges_python_basics_2018_stage01.png",
"earned_date":"2023-02-22T12:16:37.000Z",
"courses":[{"title":"Python Basics","url":"https://teamtreehouse.com/library/python-basics-3",
"badge_count":1},{"title":"Meet Python",
"url":"https://teamtreehouse.com/library/python-basics-3/meet-python",
"badge_count":1}]},{"id":16022,
"name":"Types and Branching",
"url":"https://teamtreehouse.com/library/python-basics-3/types-and-branching",
"icon_url":"https://achievement-images.teamtreehouse.com/types_and_branching.png",
"earned_date":"2023-02-22T12:16:37.000Z",
"courses":[{"title":"Python Basics",
"url":"https://teamtreehouse.com/library/python-basics-3",
"badge_count":1},{"title":"Types and Branching",
"url":"https://teamtreehouse.com/library/python-basics-3/types-and-branching",
"badge_count":1}]},
{"id":16032,
"name":"Functions and Looping",
"url":"https://teamtreehouse.com/library/python-basics-3/functions-and-looping",
"icon_url":"https://achievement-images.teamtreehouse.com/loops.png",
"earned_date":"2023-02-22T12:16:37.000Z",
"courses":[{"title":"Python Basics",
"url":"https://teamtreehouse.com/library/python-basics-3",
"badge_count":1},{"title":"Functions and Looping",
"url":"https://teamtreehouse.com/library/python-basics-3/functions-and-looping",
"badge_count":1}]},{"id":16042,"name":"All Together Now",
"url":"https://teamtreehouse.com/library/python-basics-3/all-together-now",
"icon_url":"https://achievement-images.teamtreehouse.com/all_together_now.png",
"earned_date":"2023-02-22T12:16:37.000Z",
"courses":[{"title":"Python Basics",
"url":"https://teamtreehouse.com/library/python-basics-3",
"badge_count":1},{"title":"All Together Now",
"url":"https://teamtreehouse.com/library/python-basics-3/all-together-now",
"badge_count":1}]},
{"id":16242,
"name":"Meet Lists",
"url":"https://teamtreehouse.com/library/introducing-lists/meet-lists",
"icon_url":"https://achievement-images.teamtreehouse.com/badge_introducing-lists_stage1.png",
"earned_date":"2023-02-23T02:53:58.000Z",
"courses":[{"title":"Introducing Lists",
"url":"https://teamtreehouse.com/library/introducing-lists",
"badge_count":1},
{"title":"Meet Lists",
"url":"https://teamtreehouse.com/library/introducing-lists/meet-lists",
"badge_count":1}]},
{"id":16252,
"name":"Using Lists",
"url":"https://teamtreehouse.com/library/introducing-lists/using-lists",
"icon_url":"https://achievement-images.teamtreehouse.com/badge_introducing-lists_stage2.png",
"earned_date":"2023-02-28T07:33:17.000Z",
"courses":[{"title":"Introducing Lists",
"url":"https://teamtreehouse.com/library/introducing-lists",
"badge_count":1},
{"title":"Using Lists",
"url":"https://teamtreehouse.com/library/introducing-lists/using-lists",
"badge_count":1}]},
{"id":16262,"name":"Build an Application",
"url":"https://teamtreehouse.com/library/introducing-lists/build-an-application",
"icon_url":"https://achievement-images.teamtreehouse.com/badge_introducing-lists_stage3.png",
"earned_date":"2023-02-28T11:47:37.000Z",
"courses":[{"title":"Introducing Lists",
"url":"https://teamtreehouse.com/library/introducing-lists",
"badge_count":1},
{"title":"Build an Application",
"url":"https://teamtreehouse.com/library/introducing-lists/build-an-application",
"badge_count":1}]}],
"points":{"total":621,
"HTML":0,"CSS":236,"Design":0,"JavaScript":0,"Ruby":0,"PHP":0,"Android":0,"Development Tools":0,"Business":0,"Python":355,"Java":0,"Digital Literacy":0,"C#":0,"Databases":0,"Data Analysis":0,"APIs":0,"Security":0,"Go":0,"Quality Assurance":0,"Machine Learning":0,"Learning Resources":0,"Computer Science":0,"Equity, Diversity, and Inclusion (EDI)":0,"21st Century Skills":0}}